cyp2d6_parser/__init__.py
cyp2d6_parser/__main__.py
cyp2d6_parser/allele_fxn.csv
cyp2d6_parser/common.py
cyp2d6_parser/cyp2d6_parser.py
cyp2d6_parser/genotype.py
cyp2d6_parser/parser.py
cyp2d6_parser/phenotype.py
cyp2d6_parser/utils.py
cyp2d6_parser/tests/__init__.py
cyp2d6_parser/tests/test_files.py
cyp2d6_parser/tests/test_genotype.py
cyp2d6_parser/tests/test_phenotype.py
cyp2d6_parser-2.0.3.dist-info/LICENSE
cyp2d6_parser-2.0.3.dist-info/METADATA
cyp2d6_parser-2.0.3.dist-info/WHEEL
cyp2d6_parser-2.0.3.dist-info/entry_points.txt
cyp2d6_parser-2.0.3.dist-info/top_level.txt
cyp2d6_parser-2.0.3.dist-info/RECORD
