Metadata-Version: 2.1
Name: cyp2d6-parser
Version: 2.0.3
Summary: Parser to match CYP2D6 parsing reccomendations by PharmVar.
Home-page: UNKNOWN
Author: Andrew Haddad, PharmD
Author-email: andrew.haddad@pitt.edu
License: UNKNOWN
Platform: UNKNOWN
License-File: LICENSE
Requires-Dist: pandas
Requires-Dist: numpy
